{
  "common": {
    "published": "Published {date}",
    "by": "by",
    "views": "View | Views",
    "upload": "Upload",
    "download": "Download",
    "downloads": "Download | Downloads",
    "cancel": "Cancel",
    "close": "Close",
    "delete": "Delete",
    "confirm": "Confirm",
    "save": "Save",
    "reply": "Reply",
    "vehicles": "Vehicle | Vehicles",
    "noDescription": "No description",
    "name": "Name",
    "model": "Model",
    "amount": "Amount",
    "comment": "Comment",
    "comments": "Comment | Comments",
    "maps": "Map | Maps",
    "tos": "Terms of Service",

    "toasts": {
      "success": "Success!",
      "somethingWrong": "Something went wrong!",
      "loading": "Loading..."
    }
  },

  "timeAgo": {
    "just-now": "just now",
    "ago": "{0} ago",
    "in": "in {0}",
    "last-month": "last month",
    "next-month": "next month",
    "month": "month | months",
    "last-year": "last year",
    "next-year": "next year",
    "year": "year | years",
    "yesterday": "yesterday",
    "tomorrow": "tomorrow",
    "day": "day | days",
    "last-week": "last week",
    "next-week": "next week",
    "week": "week | weeks",
    "hour": "hour | hours",
    "minute": "minute | minutes",
    "second": "second | seconds"
  },

  "navigation": {
    "home": "Home",
    "scripts": "Scripts",
    "assets": "Assets",
    "blogs": "Blogs",
    "upload": "Upload",
    "usermenu": {
      "notifications": "Notifications",
      "noRecentNotifications": "No recent noficiations",
      "seeAll": "See All",
      "markAllRead": "Mark all as read",
      "settings": "Settings",
      "myMaps": "My Maps",
      "myNotifications": "My Notifications",
      "administration": "Administration",
      "logout": "Logout"
    }
  },

  "hero": {
    "description": {
      "primary": "sharing Multi Theft Auto: San Andreas maps",
      "secondary": "easier than ever"
    }
  },

  "notifications": {
    "default": "{content}",
    "award": "Your map {ref} has received an award",
    "rated": "{user} has given a rating of {content} to {ref}",
    "commented": "{user} commented on {ref}",
    "replyToComment": "{user} replied to your comment on {ref}",
    "mapAccepted": "Your map {ref} has been accepted",
  },

  "pages": {
    "index": {
      "filterSort": {
        "results": "result | results",
        "searchPlaceholder": "Search...",
        "suggestion": "Suggestion:",
        "search": "Search",
        "searchMaps": "Search maps",
        "builtBy": "built by",
        "withTag": "with tag",
        "usingVehicle": "using vehicle",
        "sortBy": "Sort By",
        "mostRecent": "Most Recent",
        "popular": "Popular",
        "top": "Top",
        "mostAwards": "Most Awards",
        "lastUpdated": "Last Updated",
        "releaseDate": "Release Date",
        "all": "All",
        "thisYear": "This Year",
        "thisMonth": "This Month",
        "thisWeek": "This Week",
        "today": "Today"
      }
    },

    "profile": {
      "dlPack": "Download Map Pack",
      "socials": "Socials",
      "activity": "Activity",
      "noActivity": "No recent activities",
      "memberSince": "Mitglied seit",
      "mostRecentMap": "Most Recent Map",
      "noMaps": "This user has not released any maps yet.",
    },

    "map": {
      "cardTitles": {
        "comments": "Comments",
        "informations": "Map Informations",
        "authorsComment": "Authors Comment",
        "mostUsedObjects": "Most Used Objects",
        "embeddedAssets": "Embedded Assets",
        "records": "Records",
        "whoRated": "Who rated this map",
      },
      "carousel": {
        "ohNo": "Oh no!",
        "nothing": "It looks like we don't have anything to show you",
        "contact": "You can contact us on {discord} and provide videos / images"
      },
      "notApproved": "This map has not been approved yet.",
      "isPrivate": "This map is set to private.",
      "notAvailable": "This map is not available to download.",
      "browseFiles": "Browse Files",
      "getOldVersion": "Download previous versions",
      "noOldVersions": "No previous versions available",
      "noObjects": "This map has no objects.",
      "noRatings": "This map has not been rated yet.",
      "weatherID": "Weather ID {id}",
      "commentsDisabled": "Comments for this map have been disabled.",
      "addComment": "Add comment...",
      "addReply": "Reply..."
    },

    "upload": {
      "disclaimer": "Uploads are manually reviewed, this may take some time.",
      "queue": "Queue:",
      "pendingFiles": "{0} pending files",
      "browseFiles": "Browse Files",
      "dnd": "Drag & Drop files here",
      "tos": "By uploading your map(s), you agree to mtavault's {link}",
      "requirements": {
        "cardTitle": "Requirements",
        "fileType": "Must be a {extensions} file",
        "fileSize": "Must not be larger than {uploadLimit}",
        "essentials": "Essential files must be included",
        "essentialsEx": "e.g. for maps: meta.xml, *.map",
        "fileName": "Map file names should follow this format:",
        "fileNameEx": "[ARENA]Author_Author_Name.zip",
        "mapName": "Map names should follow this format:",
        "mapNameEx": "Author, Author & Author - Name"
      }
    }
  }
}
